carbonnow/__init__.py
carbonnow/client.py
carbonnow/errors.py
carbonnow-0.0.1.dist-info/LICENSE
carbonnow-0.0.1.dist-info/METADATA
carbonnow-0.0.1.dist-info/WHEEL
carbonnow-0.0.1.dist-info/top_level.txt
carbonnow-0.0.1.dist-info/RECORD
